{
  "root_dir": "/hkfs/home/project/hk-project-aimat/je7084/code/repos/rl-approx-rewards-pub/tmp/3e3dc180-e161-4fa2-9549-6e62a0f6dadb",
  "case_desc": "data sampling",
  "blc_loc_ss": [
    0.2,
    0.243,
    0.286,
    0.329,
    0.372,
    0.415,
    0.458,
    0.501,
    0.544,
    0.587,
    0.63,
    0.673,
    0.716,
    0.759,
    0.802,
    0.845
  ],
  "blc_loc_ps": [
    0.2,
    0.243,
    0.286,
    0.329,
    0.372,
    0.415,
    0.458,
    0.501,
    0.544,
    0.587,
    0.63,
    0.673,
    0.716,
    0.759,
    0.802,
    0.845
  ],
  "blc_coef_ss": [
    0.001901,
    0.002901,
    0.001901,
    0.001901,
    0.001901,
    0.001901,
    0.001901,
    0.001901,
    0.001901,
    0.001901,
    0.001901,
    0.001901,
    0.001901,
    0.001901,
    0.001901
  ],
  "blc_coef_ps": [
    -0.009101,
    -0.000101,
    -0.009101,
    -0.000101,
    -0.000101,
    -0.002101,
    -0.000101,
    -0.006101,
    -0.000101,
    -0.000101,
    -0.002101,
    -0.000101,
    -0.000101,
    -0.000101,
    -0.000101
  ],
  "cores": "48,49,50,51",
  "verbose": false,
  "label": null,
  "episode": 78889,
  "drag": 0.0137015,
  "prediction": 0.013585208915174007,
  "iterations": 1187,
  "duration": 120,
  "date": "2022-08-10 20:14:28.795216"
}