{
  "root_dir": "/hkfs/home/project/hk-project-aimat/je7084/code/repos/rl-approx-rewards-pub/tmp/d4e97b2a-4de7-4749-92a9-c1a604b2c1d0",
  "case_desc": "data sampling",
  "blc_loc_ss": [
    0.2,
    0.243,
    0.286,
    0.329,
    0.372,
    0.415,
    0.458,
    0.501,
    0.544,
    0.587,
    0.63,
    0.673,
    0.716,
    0.759,
    0.802,
    0.845
  ],
  "blc_loc_ps": [
    0.2,
    0.243,
    0.286,
    0.329,
    0.372,
    0.415,
    0.458,
    0.501,
    0.544,
    0.587,
    0.63,
    0.673,
    0.716,
    0.759,
    0.802,
    0.845
  ],
  "blc_coef_ss": [
    0.001964,
    0.002964,
    0.002964,
    0.001964,
    0.001964,
    0.001964,
    0.001964,
    0.001964,
    0.001964,
    0.001964,
    0.001964,
    0.001964,
    0.001964,
    0.001964,
    0.001964
  ],
  "blc_coef_ps": [
    -0.008298,
    -0.000298,
    -0.009298,
    -0.000298,
    -0.000298,
    -0.003298,
    -0.000298,
    -0.006298,
    -0.000298,
    -0.000298,
    -0.000298,
    -0.000298,
    -0.001298,
    -0.000298,
    -0.000298
  ],
  "cores": "36,37,38,39",
  "verbose": false,
  "label": null,
  "episode": 100430,
  "drag": 0.01360118,
  "prediction": 0.013598429039120674,
  "iterations": 1185,
  "duration": 145,
  "date": "2022-08-10 20:58:10.882890"
}