{
  "root_dir": "/hkfs/home/project/hk-project-aimat/je7084/code/repos/rl-approx-rewards-pub/tmp/befa45db-301d-4a69-b5c2-b0cc61f535f3",
  "case_desc": "data sampling",
  "blc_loc_ss": [
    0.2,
    0.243,
    0.286,
    0.329,
    0.372,
    0.415,
    0.458,
    0.501,
    0.544,
    0.587,
    0.63,
    0.673,
    0.716,
    0.759,
    0.802,
    0.845
  ],
  "blc_loc_ps": [
    0.2,
    0.243,
    0.286,
    0.329,
    0.372,
    0.415,
    0.458,
    0.501,
    0.544,
    0.587,
    0.63,
    0.673,
    0.716,
    0.759,
    0.802,
    0.845
  ],
  "blc_coef_ss": [
    0.002097,
    0.002097,
    0.002097,
    0.002097,
    0.002097,
    0.002097,
    0.002097,
    0.002097,
    0.002097,
    0.002097,
    0.002097,
    0.002097,
    0.002097,
    0.002097,
    0.002097
  ],
  "blc_coef_ps": [
    -0.00823,
    -0.00023,
    -0.00923,
    -0.00023,
    -0.00023,
    -0.00423,
    -0.00023,
    -0.00623,
    -0.00023,
    -0.00023,
    -0.00023,
    -0.00023,
    -0.00123,
    -0.00023,
    -0.00023
  ],
  "cores": "8,9,10,11",
  "verbose": false,
  "label": null,
  "episode": 94703,
  "drag": 0.01360463,
  "prediction": 0.01358878705650568,
  "iterations": 1185,
  "duration": 129,
  "date": "2022-08-10 20:45:22.114067"
}