{
  "root_dir": "/hkfs/home/project/hk-project-aimat/je7084/code/repos/rl-approx-rewards-pub/tmp/55bbf110-2516-4ff7-930f-1c6166e6c34d",
  "case_desc": "data sampling",
  "blc_loc_ss": [
    0.2,
    0.243,
    0.286,
    0.329,
    0.372,
    0.415,
    0.458,
    0.501,
    0.544,
    0.587,
    0.63,
    0.673,
    0.716,
    0.759,
    0.802,
    0.845
  ],
  "blc_loc_ps": [
    0.2,
    0.243,
    0.286,
    0.329,
    0.372,
    0.415,
    0.458,
    0.501,
    0.544,
    0.587,
    0.63,
    0.673,
    0.716,
    0.759,
    0.802,
    0.845
  ],
  "blc_coef_ss": [
    0.005215,
    0.002215,
    0.002215,
    0.002215,
    0.002215,
    0.003215,
    0.002215,
    0.002215,
    0.002215,
    0.002215,
    0.002215,
    0.002215,
    0.002215,
    0.002215,
    0.002215
  ],
  "blc_coef_ps": [
    -0.003882,
    -0.000882,
    -0.013882,
    -0.000882,
    -0.000882,
    -0.000882,
    -0.000882,
    -0.008882,
    -0.000882,
    -0.000882,
    -0.000882,
    -0.000882,
    -0.000882,
    -0.000882,
    -0.000882
  ],
  "cores": "28,29,30,31",
  "verbose": false,
  "label": null,
  "episode": 248711,
  "drag": 0.0133814,
  "prediction": 0.01336206216365099,
  "iterations": 1184,
  "duration": 131,
  "date": "2022-08-11 01:55:29.954313"
}