{
  "root_dir": "/hkfs/home/project/hk-project-aimat/je7084/code/repos/rl-approx-rewards-pub/tmp/6f2b9121-70cf-413d-8241-04779810a47d",
  "case_desc": "data sampling",
  "blc_loc_ss": [
    0.2,
    0.243,
    0.286,
    0.329,
    0.372,
    0.415,
    0.458,
    0.501,
    0.544,
    0.587,
    0.63,
    0.673,
    0.716,
    0.759,
    0.802,
    0.845
  ],
  "blc_loc_ps": [
    0.2,
    0.243,
    0.286,
    0.329,
    0.372,
    0.415,
    0.458,
    0.501,
    0.544,
    0.587,
    0.63,
    0.673,
    0.716,
    0.759,
    0.802,
    0.845
  ],
  "blc_coef_ss": [
    0.006076,
    0.002076,
    0.002076,
    0.002076,
    0.002076,
    0.004076,
    0.002076,
    0.002076,
    0.002076,
    0.002076,
    0.002076,
    0.002076,
    0.002076,
    0.002076,
    0.002076
  ],
  "blc_coef_ps": [
    -0.003076,
    -0.001076,
    -0.013076,
    -0.001076,
    -0.001076,
    -0.001076,
    -0.001076,
    -0.008076,
    -0.001076,
    -0.001076,
    -0.001076,
    -0.001076,
    -0.001076,
    -0.001076,
    -0.001076
  ],
  "cores": "32,33,34,35",
  "verbose": false,
  "label": null,
  "episode": 128835,
  "drag": 0.01339017,
  "prediction": 0.013375789858400822,
  "iterations": 1186,
  "duration": 131,
  "date": "2022-08-10 21:55:43.048416"
}