{
  "root_dir": "/hkfs/home/project/hk-project-aimat/je7084/code/repos/rl-approx-rewards-pub/tmp/f7c7593a-9492-46e3-908d-480c65cd0758",
  "case_desc": "data sampling",
  "blc_loc_ss": [
    0.2,
    0.243,
    0.286,
    0.329,
    0.372,
    0.415,
    0.458,
    0.501,
    0.544,
    0.587,
    0.63,
    0.673,
    0.716,
    0.759,
    0.802,
    0.845
  ],
  "blc_loc_ps": [
    0.2,
    0.243,
    0.286,
    0.329,
    0.372,
    0.415,
    0.458,
    0.501,
    0.544,
    0.587,
    0.63,
    0.673,
    0.716,
    0.759,
    0.802,
    0.845
  ],
  "blc_coef_ss": [
    0.008,
    0.002,
    0.002,
    0.002,
    0.002,
    0.003,
    0.002,
    0.002,
    0.002,
    0.002,
    0.002,
    0.002,
    0.002,
    0.002,
    0.002
  ],
  "blc_coef_ps": [
    -0.004067,
    -0.001067,
    -0.008067,
    -0.001067,
    -0.001067,
    -0.001067,
    -0.001067,
    -0.012067,
    -0.001067,
    -0.001067,
    -0.001067,
    -0.001067,
    -0.001067,
    -0.001067,
    -0.001067
  ],
  "cores": "16,17,18,19",
  "verbose": false,
  "label": null,
  "episode": 94983,
  "drag": 0.01339423,
  "prediction": 0.013371096923947334,
  "iterations": 1185,
  "duration": 130,
  "date": "2022-08-10 20:48:51.417951"
}