{
  "root_dir": "/hkfs/home/project/hk-project-aimat/je7084/code/repos/rl-approx-rewards-pub/tmp/c14ded4c-416a-437a-8462-7fe28e1289c8",
  "case_desc": "data sampling",
  "blc_loc_ss": [
    0.2,
    0.243,
    0.286,
    0.329,
    0.372,
    0.415,
    0.458,
    0.501,
    0.544,
    0.587,
    0.63,
    0.673,
    0.716,
    0.759,
    0.802,
    0.845
  ],
  "blc_loc_ps": [
    0.2,
    0.243,
    0.286,
    0.329,
    0.372,
    0.415,
    0.458,
    0.501,
    0.544,
    0.587,
    0.63,
    0.673,
    0.716,
    0.759,
    0.802,
    0.845
  ],
  "blc_coef_ss": [
    0.006219,
    0.002219,
    0.002219,
    0.002219,
    0.002219,
    0.002219,
    0.002219,
    0.002219,
    0.002219,
    0.002219,
    0.002219,
    0.002219,
    0.002219,
    0.002219,
    0.002219
  ],
  "blc_coef_ps": [
    -0.003819,
    -0.000819,
    -0.012819,
    -0.000819,
    -0.000819,
    -0.001819,
    -0.000819,
    -0.009819,
    -0.000819,
    -0.000819,
    -0.000819,
    -0.000819,
    -0.000819,
    -0.000819,
    -0.000819
  ],
  "cores": "8,9,10,11",
  "verbose": false,
  "label": null,
  "episode": 246888,
  "drag": 0.01337098,
  "prediction": 0.013358919881284237,
  "iterations": 1184,
  "duration": 130,
  "date": "2022-08-11 01:52:03.776296"
}