{
  "root_dir": "/hkfs/home/project/hk-project-aimat/je7084/code/repos/rl-approx-rewards-pub/tmp/9b3618b9-cc8d-4647-a4e1-b4d52d1a3019",
  "case_desc": "data sampling",
  "blc_loc_ss": [
    0.2,
    0.243,
    0.286,
    0.329,
    0.372,
    0.415,
    0.458,
    0.501,
    0.544,
    0.587,
    0.63,
    0.673,
    0.716,
    0.759,
    0.802,
    0.845
  ],
  "blc_loc_ps": [
    0.2,
    0.243,
    0.286,
    0.329,
    0.372,
    0.415,
    0.458,
    0.501,
    0.544,
    0.587,
    0.63,
    0.673,
    0.716,
    0.759,
    0.802,
    0.845
  ],
  "blc_coef_ss": [
    0.002072,
    0.002072,
    0.002072,
    0.002072,
    0.002072,
    0.002072,
    0.002072,
    0.002072,
    0.002072,
    0.002072,
    0.002072,
    0.002072,
    0.002072,
    0.002072,
    0.002072
  ],
  "blc_coef_ps": [
    -0.012139,
    -0.000139,
    -0.012139,
    -0.000139,
    -0.000139,
    -0.004139,
    -0.000139,
    -0.000139,
    -0.000139,
    -0.000139,
    -0.000139,
    -0.000139,
    -0.001139,
    -0.000139,
    -0.000139
  ],
  "cores": "28,29,30,31",
  "verbose": false,
  "label": null,
  "episode": 66601,
  "drag": 0.01368405,
  "prediction": 0.013821590691804886,
  "iterations": 1185,
  "duration": 131,
  "date": "2022-08-10 19:47:18.509729"
}