{
  "root_dir": "/hkfs/home/project/hk-project-aimat/je7084/code/repos/rl-approx-rewards-pub/tmp/a796f1c9-2b62-4676-a289-ca4d75384505",
  "case_desc": "data sampling",
  "blc_loc_ss": [
    0.2,
    0.243,
    0.286,
    0.329,
    0.372,
    0.415,
    0.458,
    0.501,
    0.544,
    0.587,
    0.63,
    0.673,
    0.716,
    0.759,
    0.802,
    0.845
  ],
  "blc_loc_ps": [
    0.2,
    0.243,
    0.286,
    0.329,
    0.372,
    0.415,
    0.458,
    0.501,
    0.544,
    0.587,
    0.63,
    0.673,
    0.716,
    0.759,
    0.802,
    0.845
  ],
  "blc_coef_ss": [
    0.001933,
    0.002933,
    0.001933,
    0.001933,
    0.001933,
    0.001933,
    0.001933,
    0.001933,
    0.001933,
    0.001933,
    0.001933,
    0.001933,
    0.001933,
    0.001933,
    0.001933
  ],
  "blc_coef_ps": [
    -0.014133,
    -0.000133,
    -0.010133,
    -0.000133,
    -0.000133,
    -0.001133,
    -0.000133,
    -0.000133,
    -0.000133,
    -0.000133,
    -0.002133,
    -0.000133,
    -0.001133,
    -0.000133,
    -0.000133
  ],
  "cores": "32,33,34,35",
  "verbose": false,
  "label": null,
  "episode": 66962,
  "drag": 0.01374643,
  "prediction": 0.013823173008859158,
  "iterations": 1188,
  "duration": 133,
  "date": "2022-08-10 19:47:32.219451"
}