{
  "root_dir": "/hkfs/home/project/hk-project-aimat/je7084/code/repos/rl-approx-rewards-pub/tmp/9a10d46f-a95b-42dc-b2a2-bdae8c231cd4",
  "case_desc": "data sampling",
  "blc_loc_ss": [
    0.2,
    0.243,
    0.286,
    0.329,
    0.372,
    0.415,
    0.458,
    0.501,
    0.544,
    0.587,
    0.63,
    0.673,
    0.716,
    0.759,
    0.802,
    0.845
  ],
  "blc_loc_ps": [
    0.2,
    0.243,
    0.286,
    0.329,
    0.372,
    0.415,
    0.458,
    0.501,
    0.544,
    0.587,
    0.63,
    0.673,
    0.716,
    0.759,
    0.802,
    0.845
  ],
  "blc_coef_ss": [
    0.002017,
    0.002017,
    0.002017,
    0.002017,
    0.002017,
    0.002017,
    0.002017,
    0.002017,
    0.002017,
    0.002017,
    0.002017,
    0.002017,
    0.002017,
    0.002017,
    0.002017
  ],
  "blc_coef_ps": [
    -0.010083,
    -8.3e-05,
    -0.017083,
    -8.3e-05,
    -8.3e-05,
    -0.001083,
    -8.3e-05,
    -8.3e-05,
    -8.3e-05,
    -8.3e-05,
    -8.3e-05,
    -8.3e-05,
    -0.001083,
    -8.3e-05,
    -8.3e-05
  ],
  "cores": "4,5,6,7",
  "verbose": false,
  "label": null,
  "episode": 207794,
  "drag": 0.01375045,
  "prediction": 0.01382017508149147,
  "iterations": 1185,
  "duration": 129,
  "date": "2022-08-10 23:55:57.027656"
}