{
  "root_dir": "/hkfs/home/project/hk-project-aimat/je7084/code/repos/rl-approx-rewards-pub/tmp/7460c652-cbbf-4f49-8599-5ebd7f5ce86b",
  "case_desc": "data sampling",
  "blc_loc_ss": [
    0.2,
    0.243,
    0.286,
    0.329,
    0.372,
    0.415,
    0.458,
    0.501,
    0.544,
    0.587,
    0.63,
    0.673,
    0.716,
    0.759,
    0.802,
    0.845
  ],
  "blc_loc_ps": [
    0.2,
    0.243,
    0.286,
    0.329,
    0.372,
    0.415,
    0.458,
    0.501,
    0.544,
    0.587,
    0.63,
    0.673,
    0.716,
    0.759,
    0.802,
    0.845
  ],
  "blc_coef_ss": [
    0.001994,
    0.001994,
    0.001994,
    0.001994,
    0.001994,
    0.001994,
    0.001994,
    0.003994,
    0.001994,
    0.002994,
    0.001994,
    0.001994,
    0.001994,
    0.001994,
    0.001994
  ],
  "blc_coef_ps": [
    -0.010461,
    -0.000461,
    -0.012461,
    -0.000461,
    -0.002461,
    -0.001461,
    -0.000461,
    -0.001461,
    -0.000461,
    -0.000461,
    -0.000461,
    -0.000461,
    -0.000461,
    -0.000461,
    -0.000461
  ],
  "cores": "36,37,38,39",
  "verbose": false,
  "label": null,
  "episode": 13119,
  "drag": 0.01361559,
  "prediction": 0.013830644078552723,
  "iterations": 1185,
  "duration": 129,
  "date": "2022-08-10 18:10:39.315992"
}