{
  "root_dir": "/hkfs/home/project/hk-project-aimat/je7084/code/repos/rl-approx-rewards-pub/tmp/fa0d3ac6-5e67-4e01-8b86-67845c503a75",
  "case_desc": "data sampling",
  "blc_loc_ss": [
    0.2,
    0.243,
    0.286,
    0.329,
    0.372,
    0.415,
    0.458,
    0.501,
    0.544,
    0.587,
    0.63,
    0.673,
    0.716,
    0.759,
    0.802,
    0.845
  ],
  "blc_loc_ps": [
    0.2,
    0.243,
    0.286,
    0.329,
    0.372,
    0.415,
    0.458,
    0.501,
    0.544,
    0.587,
    0.63,
    0.673,
    0.716,
    0.759,
    0.802,
    0.845
  ],
  "blc_coef_ss": [
    0.001627,
    0.001627,
    0.001627,
    0.001627,
    0.001627,
    0.001627,
    0.001627,
    0.001627,
    0.001627,
    0.002627,
    0.001627,
    0.001627,
    0.001627,
    0.001627,
    0.001627
  ],
  "blc_coef_ps": [
    -0.009827,
    0.000173,
    -0.007827,
    0.000173,
    0.000173,
    0.000173,
    0.000173,
    -0.008827,
    0.000173,
    0.000173,
    0.000173,
    0.000173,
    -0.000827,
    0.000173,
    0.000173
  ],
  "cores": "12,13,14,15",
  "verbose": false,
  "label": null,
  "episode": 35927,
  "drag": 0.01394929,
  "prediction": 0.013823800720274448,
  "iterations": 1187,
  "duration": 131,
  "date": "2022-08-10 18:51:44.354808"
}