{
  "root_dir": "/hkfs/home/project/hk-project-aimat/je7084/code/repos/rl-approx-rewards-pub/tmp/0864b47e-c24f-437d-a695-fd4cce99c3db",
  "case_desc": "data sampling",
  "blc_loc_ss": [
    0.2,
    0.243,
    0.286,
    0.329,
    0.372,
    0.415,
    0.458,
    0.501,
    0.544,
    0.587,
    0.63,
    0.673,
    0.716,
    0.759,
    0.802,
    0.845
  ],
  "blc_loc_ps": [
    0.2,
    0.243,
    0.286,
    0.329,
    0.372,
    0.415,
    0.458,
    0.501,
    0.544,
    0.587,
    0.63,
    0.673,
    0.716,
    0.759,
    0.802,
    0.845
  ],
  "blc_coef_ss": [
    0.001509,
    0.001509,
    0.001509,
    0.001509,
    0.001509,
    0.001509,
    0.001509,
    0.001509,
    0.001509,
    0.001509,
    0.001509,
    0.001509,
    0.001509,
    0.001509,
    0.001509
  ],
  "blc_coef_ps": [
    -0.007575,
    0.000425,
    -0.013575,
    0.000425,
    0.000425,
    -0.003575,
    0.000425,
    -0.002575,
    0.000425,
    0.000425,
    0.000425,
    0.000425,
    0.000425,
    0.000425,
    0.000425
  ],
  "cores": "44,45,46,47",
  "verbose": false,
  "label": null,
  "episode": 240730,
  "drag": 0.01410657,
  "prediction": 0.013816816732287407,
  "iterations": 1190,
  "duration": 119,
  "date": "2022-08-11 00:54:53.716325"
}