{
  "root_dir": "/hkfs/home/project/hk-project-aimat/je7084/code/repos/rl-approx-rewards-pub/tmp/9a72f631-183d-431c-a97d-890fadd2e7cf",
  "case_desc": "data sampling",
  "blc_loc_ss": [
    0.2,
    0.243,
    0.286,
    0.329,
    0.372,
    0.415,
    0.458,
    0.501,
    0.544,
    0.587,
    0.63,
    0.673,
    0.716,
    0.759,
    0.802,
    0.845
  ],
  "blc_loc_ps": [
    0.2,
    0.243,
    0.286,
    0.329,
    0.372,
    0.415,
    0.458,
    0.501,
    0.544,
    0.587,
    0.63,
    0.673,
    0.716,
    0.759,
    0.802,
    0.845
  ],
  "blc_coef_ss": [
    0.001579,
    0.001579,
    0.001579,
    0.001579,
    0.001579,
    0.001579,
    0.001579,
    0.001579,
    0.001579,
    0.001579,
    0.001579,
    0.001579,
    0.001579,
    0.001579,
    0.001579
  ],
  "blc_coef_ps": [
    -0.006645,
    0.000355,
    -0.014645,
    0.000355,
    0.000355,
    -0.001645,
    0.000355,
    -0.004645,
    0.000355,
    0.000355,
    0.000355,
    0.000355,
    0.000355,
    0.000355,
    0.000355
  ],
  "cores": "40,41,42,43",
  "verbose": false,
  "label": null,
  "episode": 135896,
  "drag": 0.01404799,
  "prediction": 0.013818016275763512,
  "iterations": 1189,
  "duration": 118,
  "date": "2022-08-10 21:48:18.517686"
}