{
  "root_dir": "/hkfs/home/project/hk-project-aimat/je7084/code/repos/rl-approx-rewards-pub/tmp/e9125194-500c-4e80-946f-409ad0ed3fdd",
  "case_desc": "data sampling",
  "blc_loc_ss": [
    0.2,
    0.243,
    0.286,
    0.329,
    0.372,
    0.415,
    0.458,
    0.501,
    0.544,
    0.587,
    0.63,
    0.673,
    0.716,
    0.759,
    0.802,
    0.845
  ],
  "blc_loc_ps": [
    0.2,
    0.243,
    0.286,
    0.329,
    0.372,
    0.415,
    0.458,
    0.501,
    0.544,
    0.587,
    0.63,
    0.673,
    0.716,
    0.759,
    0.802,
    0.845
  ],
  "blc_coef_ss": [
    0.001646,
    0.001646,
    0.001646,
    0.001646,
    0.001646,
    0.001646,
    0.001646,
    0.001646,
    0.001646,
    0.001646,
    0.001646,
    0.001646,
    0.001646,
    0.001646,
    0.001646
  ],
  "blc_coef_ps": [
    -0.009712,
    0.000288,
    -0.011712,
    0.000288,
    0.000288,
    0.000288,
    0.000288,
    -0.006712,
    0.000288,
    0.000288,
    0.000288,
    0.000288,
    0.000288,
    0.000288,
    0.000288
  ],
  "cores": "48,49,50,51",
  "verbose": false,
  "label": null,
  "episode": 92156,
  "drag": 0.01400017,
  "prediction": 0.01381829846650362,
  "iterations": 1191,
  "duration": 121,
  "date": "2022-08-10 20:30:44.267330"
}